{
  "$schema": "https://json-schema.org/draft/2020-12/schema",
  "title": "Bid",
  "description": "Brand Agent bid submitted in response to a ContextRequest",
  "type": "object",
  "required": [
    "bid_id",
    "brand_agent_id",
    "context_id",
    "wallet_id",
    "pricing",
    "offer",
    "timestamp",
    "auth"
  ],
  "properties": {
    "bid_id": {
      "type": "string",
      "description": "Unique identifier for this bid",
      "example": "bid_7823"
    },
    "brand_agent_id": {
      "type": "string",
      "description": "Identifier of the brand agent placing the bid",
      "example": "brand_agent_123"
    },
    "context_id": {
      "type": "string",
      "description": "ID of the ContextRequest being bid on",
      "example": "ctx_92f"
    },
    "wallet_id": {
      "type": "string",
      "description": "Wallet to debit if the bid wins",
      "example": "wallet_890"
    },
    "pricing": {
      "type": "object",
      "description": "Pricing vector for different billing events. All amounts in USD micros (1 USD = 1,000,000 micros).",
      "required": ["cpx_micros"],
      "properties": {
        "cpx_micros": {
          "type": "integer",
          "minimum": 0,
          "description": "Price per exposure in USD micros (int64, authoritative)",
          "example": 50000
        },
        "cpc_micros": {
          "type": "integer",
          "minimum": 0,
          "description": "Price per click in USD micros (int64, optional)",
          "example": 450000
        },
        "cpa_micros": {
          "type": "integer",
          "minimum": 0,
          "description": "Price per conversion in USD micros (int64, optional)",
          "example": 10000000
        },
        "preferred_pricing_model": {
          "type": "string",
          "description": "Preferred pricing model for billing (CPX, CPC, or CPA)",
          "enum": ["CPX", "CPC", "CPA"],
          "example": "CPA"
        },
        "display": {
          "type": "object",
          "description": "Optional display metadata for UI purposes only (non-normative, ignored by auction)",
          "properties": {
            "currency": {
              "type": "string",
              "pattern": "^[A-Z]{3}$",
              "description": "Display currency code (ISO 4217)",
              "example": "INR"
            },
            "cpx_label": {
              "type": "string",
              "description": "Display label for CPX price",
              "example": "₹1.25"
            },
            "cpc_label": {
              "type": "string",
              "description": "Display label for CPC price",
              "example": "₹11.25"
            },
            "cpa_label": {
              "type": "string",
              "description": "Display label for CPA price",
              "example": "₹250"
            }
          },
          "additionalProperties": false
        }
      },
      "additionalProperties": false
    },
    "offer": {
      "type": "object",
      "description": "Offer metadata that will be rendered to the user if the bid wins",
      "required": ["creative_input"],
      "properties": {
        "creative_input": {
          "$ref": "./creative-input.json"
        }
      },
      "additionalProperties": false
    },
    "timestamp": {
      "type": "string",
      "format": "date-time",
      "description": "ISO 8601 timestamp when the bid was generated",
      "example": "2025-11-11T18:00:01Z"
    },
    "auth": {
      "type": "object",
      "description": "Authentication envelope used for replay protection",
      "required": ["nonce", "signature"],
      "properties": {
        "nonce": {
          "type": "string",
          "description": "One-time nonce for replay protection",
          "example": "nonce_456"
        },
        "signature": {
          "type": "string",
          "description": "Signature over the canonical bid payload",
          "example": "sig_789"
        }
      },
      "additionalProperties": false
    },
    "metadata": {
      "$ref": "./common.json#/definitions/extensionNamespace",
      "description": "Optional vendor-namespaced metadata"
    },
    "processing_latency_ms": {
      "type": "integer",
      "description": "Round-trip latency from auction request receipt to bid submission (milliseconds). Used by operator to track brand agent response times.",
      "minimum": 0,
      "example": 42
    }
  },
  "examples": [
    {
      "bid_id": "bid_7823",
      "brand_agent_id": "brand_agent_123",
      "context_id": "ctx_92f",
      "wallet_id": "wallet_890",
      "pricing": {
        "cpx_micros": 50000,
        "cpc_micros": 450000,
        "cpa_micros": 10000000,
        "preferred_pricing_model": "CPA",
        "display": {
          "currency": "INR",
          "cpx_label": "₹1.25",
          "cpc_label": "₹11.25",
          "cpa_label": "₹250"
        }
      },
      "offer": {
        "creative_input": {
          "brand_name": "Nimbus",
          "product_name": "Nimbus CRM Pro",
          "short_description": "CRM built for growing teams, with AI-assisted workflows.",
          "long_description": "Nimbus CRM Pro is designed for teams of 5-50 people who need intelligent pipeline management. It includes automated follow-ups, collaborative forecasting, and embedded AI copilots that help close deals faster.",
          "value_props": ["Automated follow-ups", "Embedded copilots"],
          "context_snippet": "For startups needing higher limits and automated expense workflows.",
          "cta_label": "Start Free Trial",
          "cta_url": "https://nimbus.example.com/signup",
          "assets": {
            "logo_url": "https://cdn.example.com/nimbus/logo.png",
            "image_urls": ["https://cdn.example.com/nimbus/crm.png"],
            "resource_urls": ["https://nimbus.example.com/signup"]
          }
        }
      },
      "timestamp": "2025-11-11T18:00:01Z",
      "auth": {
        "nonce": "nonce_456",
        "signature": "sig_789"
      },
      "processing_latency_ms": 42
    }
  ],
  "$id": "https://aip.org/schemas/bid.json"
}
